maven_artifact/__init__.py
maven_artifact/artifact.py
maven_artifact/downloader.py
maven_artifact/main.py
maven_artifact/requestor.py
maven_artifact/resolver.py
maven_artifact/utils.py
maven_artifact-0.3.5.dist-info/METADATA
maven_artifact-0.3.5.dist-info/WHEEL
maven_artifact-0.3.5.dist-info/entry_points.txt
maven_artifact-0.3.5.dist-info/RECORD
